ngdataenginterface/.DS_Store
ngdataenginterface/__init__.py
ngdataenginterface/analytical.py
ngdataenginterface/aws_interface.py
ngdataenginterface/process.py
ngdataenginterface/scripts/__init__.py
ngdataenginterface/scripts/create_analytical_tables.py
ngdataenginterface/scripts/landing_to_raw.py
ngdataenginterface/scripts/raw_to_trusted.py
ngdataenginterface/scripts/trusted_to_analytics.py
ngdataenginterface/spark_manager.py
ngdataenginterface/table.py
ngdataenginterface/utils.py
ngdataenginterface-0.1.8.dist-info/METADATA
ngdataenginterface-0.1.8.dist-info/WHEEL
ngdataenginterface-0.1.8.dist-info/RECORD
