Metadata-Version: 2.1
Name: ngdataenginterface
Version: 0.1.8
Summary: A library for facilitating the development of data engineering pipelines
Author: NG.CASH
Requires-Python: >=3.7,<4.0
Classifier: Programming Language :: Python :: 3
Classifier: Programming Language :: Python :: 3.7
Classifier: Programming Language :: Python :: 3.8
Classifier: Programming Language :: Python :: 3.9
Classifier: Programming Language :: Python :: 3.10
Classifier: Programming Language :: Python :: 3.11
Classifier: Programming Language :: Python :: 3.12
Requires-Dist: boto3 (==1.26.135)
Requires-Dist: pytest (==7.3.1)
Requires-Dist: pytest-cov (==4.0.0)
